{
  "error"          : false,
  "id"             : "212fca7b37ef95bef875c6df807a4dacd1f47917bb9f786fc557495409169be9",
  "filename"       : "Nusantara_v1.0-platina-08082020-OFFICIAL-1051.zip",
  "datetime"       : 1596883850,
  "version"        : "1.0",
  "size"           : 863226274,
  "url"            : "https://sourceforge.net/projects/nusantaraproject/files/platina/Nusantara_v1.0-platina-08082020-OFFICIAL-1051.zip/download",
  "filehash"       : "02fa8da164d47692f315c8f2664403f6",
  "website_url"    : "https://comingsoon",
  "news_url"       : "https://t.me/NusantaraUpdates",
  "donate_url"     : "https://www.paypal.me/1cecreamm",
  "maintainer"     : "1cecreamm",
  "maintainer_url" : "https://github.com/1cecreamm",
  "forum_url"      : "https://t.me/NusantaraCommunity"
}
